approxKD/__init__.py
approxKD/ann.py
approxKD/exception.py
approxKD/logger.py
approxKD/tree.py
approxKD/utils.py
approxKD-0.0.0.dist-info/METADATA
approxKD-0.0.0.dist-info/WHEEL
approxKD-0.0.0.dist-info/top_level.txt
approxKD-0.0.0.dist-info/RECORD
