Metadata-Version: 2.1
Name: approxKD
Version: 0.0.0
Summary: A python package that implements Approximate Nearest Neighbor algorithm using KD-Trees in python
Home-page: https://github.com/prxdyu/approxKD
Author: prxdyu
Author-email: pradyu1742@gmail.com
License: MIT
Project-URL: Bug Tracker, https://github.com/prxdyu/approxKD/issues
Classifier: Programming Language :: Python :: 3.7
Classifier: Programming Language :: Python :: 3.8
Classifier: Programming Language :: Python :: 3.9
Classifier: Operating System :: OS Independent
Requires-Python: >=3.7
Requires-Dist: numpy
Requires-Dist: scipy
Requires-Dist: tqdm
Provides-Extra: testing
Requires-Dist: pytest>=7.1.3; extra == "testing"
Requires-Dist: mypy>=0.971; extra == "testing"
Requires-Dist: flake8>=5.0.4; extra == "testing"
Requires-Dist: tox>=3.25.1; extra == "testing"
Requires-Dist: black>=22.8.0; extra == "testing"
